AUTHORS.rst
CONTRIBUTING.rst
HISTORY.rst
LICENSE
MANIFEST.in
README.rst
setup.cfg
setup.py
confcall/__init__.py
confcall/confcall.py
confcall.egg-info/PKG-INFO
confcall.egg-info/SOURCES.txt
confcall.egg-info/dependency_links.txt
confcall.egg-info/not-zip-safe
confcall.egg-info/top_level.txt
docs/Makefile
docs/authors.rst
docs/conf.py
docs/contributing.rst
docs/history.rst
docs/index.rst
docs/installation.rst
docs/make.bat
docs/readme.rst
docs/usage.rst
tests/test_confcall.py